README.rst
setup.py
nginc/__init__.py
nginc/nginx.conf
nginc.egg-info/PKG-INFO
nginc.egg-info/SOURCES.txt
nginc.egg-info/dependency_links.txt
nginc.egg-info/entry_points.txt
nginc.egg-info/requires.txt
nginc.egg-info/top_level.txt