Metadata-Version: 1.1
Name: nginc
Version: 0.0.3
Summary: run nginx from the commandline
Home-page: https://github.com/FlorianLudwig/nginc
Author: Florian Ludwig
Author-email: f.ludwig@greyrook.com
License: http://www.apache.org/licenses/LICENSE-2.0
Platform: UNKNOWN
Classifier: License :: OSI Approved :: Apache Software License
Classifier: Programming Language :: Python :: 2.7
